elephant_parsel/__init__.py
elephant_parsel/postgres_db.py
elephant_parsel-1.2.1.dist-info/METADATA
elephant_parsel-1.2.1.dist-info/WHEEL
elephant_parsel-1.2.1.dist-info/licenses/LICENSE
elephant_parsel-1.2.1.dist-info/RECORD
