Metadata-Version: 2.1
Name: elephant_parsel
Version: 1.2.1
Summary: wrapper for PostgreSQL queries with transaction and connection pooling support
Project-URL: Homepage, https://github.com/betanummeric/elephant_parsel
Project-URL: Bug Tracker, https://github.com/betanummeric/elephant_parsel/issues
Project-URL: Documentation, https://elephant-parsel.readthedocs.io/en/latest/
Author-email: betanummeric <40263343+betanummeric@users.noreply.github.com>
License-File: LICENSE
Classifier: License :: OSI Approved :: MIT License
Classifier: Operating System :: OS Independent
Classifier: Programming Language :: Python :: 3
Requires-Python: >=3.7
Requires-Dist: psycopg2>=2.7.0
